setup.py
probability_distributions_2020_1/Binomialdistribution.py
probability_distributions_2020_1/Gaussiandistribution.py
probability_distributions_2020_1/Generaldistribution.py
probability_distributions_2020_1/__init__.py
probability_distributions_2020_1.egg-info/PKG-INFO
probability_distributions_2020_1.egg-info/SOURCES.txt
probability_distributions_2020_1.egg-info/dependency_links.txt
probability_distributions_2020_1.egg-info/not-zip-safe
probability_distributions_2020_1.egg-info/top_level.txt