Metadata-Version: 1.0
Name: probability-distributions-2020-1
Version: 0.1
Summary: Gaussian distributions
Home-page: UNKNOWN
Author: Sourav Sharma
Author-email: sourav.sharma479@gmail.com
License: UNKNOWN
Platform: UNKNOWN
